npc_gzip/__init__.py
npc_gzip/aggregations.py
npc_gzip/compressors/__init__.py
npc_gzip/compressors/base.py
npc_gzip/compressors/bz2_compressor.py
npc_gzip/compressors/gzip_compressor.py
npc_gzip/compressors/lzma_compressor.py
npc_gzip/distance.py
npc_gzip/exceptions.py
npc_gzip/knn_classifier.py
npc_gzip/utils.py
npc_gzip-0.1.1.dist-info/LICENSE
npc_gzip-0.1.1.dist-info/METADATA
npc_gzip-0.1.1.dist-info/WHEEL
npc_gzip-0.1.1.dist-info/RECORD
