Metadata-Version: 2.1
Name: npc-gzip
Version: 0.1.1
Summary: Code for Paper: “Low-Resource” Text Classification: A Parameter-Free Classification Method with Compressors
Home-page: https://github.com/bazingagin/npc_gzip
License: MIT
Keywords: npc_gzip,knn-gzip
Author: Gin Jiang
Author-email: bazingagin@gmail.com
Maintainer: Zach Bloss
Maintainer-email: zacharybloss@gmail.com
Requires-Python: >=3.9,<4.0
Classifier: License :: OSI Approved :: MIT License
Classifier: Programming Language :: Python :: 3
Classifier: Programming Language :: Python :: 3.9
Classifier: Programming Language :: Python :: 3.10
Classifier: Programming Language :: Python :: 3.11
Requires-Dist: numpy (>=1.25.2,<2.0.0)
Requires-Dist: tqdm (>=4.65.0,<5.0.0)
Project-URL: Repository, https://github.com/bazingagin/npc_gzip
